{"order_id": "5b3aae26-4844-11ee-aa37-00155d2a76eb", "order_total": 8990, "product_info": {"product_id": "1053e26d-7224-4247-9729-1cf4dd4a7987", "product_description": "Memória Gamer Husky"}, "customer_info": {"customer_id": "05296fc9-b5eb-48ba-a182-b28334150741", "customer_name": "Luana Freitas", "customer_phone_number": "(071) 3763 4311"}, "payment_info": {"payment_type": "credit_card", "card_number": "676269883754", "provider": "VISA 16 digit", "expire": "12/32", "security_code": "848"}, "delivery_address": {"zip_code": "22488816", "country": "Brazil", "state": "Mato Grosso do Sul", "city": "Nascimento", "street": "Jardim Heitor Sales", "number": "18"}, "order_created_at": "2023-05-22 10:30:04"}