{"order_id": "5c1a4824-4844-11ee-aa37-00155d2a76eb", "order_total": 8990, "product_info": {"product_id": "1053e26d-7224-4247-9729-1cf4dd4a7987", "product_description": "Memória Gamer Husky"}, "customer_info": {"customer_id": "91f768b2-0fbf-4879-83a7-ca1fae1a380e", "customer_name": "Daniel da Mota", "customer_phone_number": "0300 597 9562"}, "payment_info": {"payment_type": "credit_card", "card_number": "30405942510848", "provider": "VISA 16 digit", "expire": "08/29", "security_code": "123"}, "delivery_address": {"zip_code": "60310508", "country": "Brazil", "state": "Ceará", "city": "da Rosa do Oeste", "street": "Feira Jesus", "number": "12"}, "order_created_at": "2023-05-22 17:19:01"}