{"order_id": "486c2338-4844-11ee-aa37-00155d2a76eb", "order_total": 59999, "product_info": {"product_id": "fa03e226-fa16-4d08-ab4b-73d73ef98861", "product_description": "Tablet Samsung Galaxy"}, "customer_info": {"customer_id": "6219d2c8-273a-4f26-8446-ba44d260cd4a", "customer_name": "Murilo Cunha", "customer_phone_number": "(081) 3362 1118"}, "payment_info": {"payment_type": "credit_card", "card_number": "4882142887359367", "provider": "Mastercard", "expire": "09/30", "security_code": "577"}, "delivery_address": {"zip_code": "65865526", "country": "Brazil", "state": "Roraima", "city": "Costa das Pedras", "street": "Loteamento de da Costa", "number": "652"}, "order_created_at": "2023-05-05 05:18:32"}