{"order_id": "60847ff6-4844-11ee-aa37-00155d2a76eb", "order_total": 149999, "product_info": {"product_id": "e91cb273-e2d0-4f35-958f-8b406a1e53d6", "product_description": "Monitor Gamer Asus"}, "customer_info": {"customer_id": "4f788604-dd91-4385-8688-584531bdc27f", "customer_name": "Maria Julia da Rocha", "customer_phone_number": "61 0442-8928"}, "payment_info": {"payment_type": "credit_card", "card_number": "30342046523759", "provider": "JCB 16 digit", "expire": "10/32", "security_code": "6309"}, "delivery_address": {"zip_code": "08768202", "country": "Brazil", "state": "São Paulo", "city": "da Mata da Mata", "street": "Aeroporto Fernandes", "number": "94"}, "order_created_at": "2023-05-26 08:57:26"}