{"order_id": "46858de8-4844-11ee-aa37-00155d2a76eb", "order_total": 70000, "product_info": {"product_id": "38d2d1cc-007b-4187-bab2-6644b50a82cf", "product_description": "Smartwatch Hit"}, "customer_info": {"customer_id": "5a321929-49fb-466c-a409-6f2aa39eafd0", "customer_name": "Heloísa Vieira", "customer_phone_number": "+55 (081) 8506 0477"}, "payment_info": {"payment_type": "credit_card", "card_number": "4186638829049505030", "provider": "Maestro", "expire": "11/32", "security_code": "138"}, "delivery_address": {"zip_code": "70358820", "country": "Brazil", "state": "Distrito Federal", "city": "Caldeira da Praia", "street": "Sítio da Cruz", "number": "2"}, "order_created_at": "2023-05-04 23:53:06"}