{"order_id": "48ac3586-4844-11ee-aa37-00155d2a76eb", "order_total": 34290, "product_info": {"product_id": "a20d3514-3a01-4fe4-87cf-2d765bf641ef", "product_description": "HD Toshiba L200"}, "customer_info": {"customer_id": "30f239f1-3cf2-44b2-a474-13cab6d6d1c6", "customer_name": "Vinicius Jesus", "customer_phone_number": "31 4818 0216"}, "payment_info": {"payment_type": "credit_card", "card_number": "2428816422949759", "provider": "Diners Club / Carte Blanche", "expire": "02/31", "security_code": "954"}, "delivery_address": {"zip_code": "16678490", "country": "Brazil", "state": "Pará", "city": "da Rosa da Mata", "street": "Quadra de Freitas", "number": "57"}, "order_created_at": "2023-05-06 11:04:17"}