{"order_id": "50ffdd64-4844-11ee-aa37-00155d2a76eb", "order_total": 8990, "product_info": {"product_id": "1053e26d-7224-4247-9729-1cf4dd4a7987", "product_description": "Memória Gamer Husky"}, "customer_info": {"customer_id": "fa28a5e7-9a3e-4e7c-b7b9-0f4c9ee770c8", "customer_name": "Marcelo da Mata", "customer_phone_number": "0900-127-0463"}, "payment_info": {"payment_type": "credit_card", "card_number": "3508974209061446", "provider": "Mastercard", "expire": "06/28", "security_code": "569"}, "delivery_address": {"zip_code": "29168816", "country": "Brazil", "state": "Ceará", "city": "da Costa das Flores", "street": "Rua de Azevedo", "number": "32"}, "order_created_at": "2023-05-13 21:03:18"}