{"order_id": "623e93fe-4844-11ee-aa37-00155d2a76eb", "order_total": 259980, "product_info": {"product_id": "5ece571b-65fe-47ce-96e0-17cf1c67fe0c", "product_description": "Smart TV Samsung"}, "customer_info": {"customer_id": "dec29d48-1a76-4ed1-aed6-f27700a80517", "customer_name": "Vitor Caldeira", "customer_phone_number": "(031) 5653-4432"}, "payment_info": {"payment_type": "credit_card", "card_number": "6011090500850792", "provider": "VISA 16 digit", "expire": "06/27", "security_code": "555"}, "delivery_address": {"zip_code": "97574493", "country": "Brazil", "state": "Distrito Federal", "city": "Oliveira de Souza", "street": "Condomínio da Cruz", "number": "479"}, "order_created_at": "2023-05-28 11:51:15"}