{"order_id": "62b676c6-4844-11ee-aa37-00155d2a76eb", "order_total": 350050, "product_info": {"product_id": "41811051-edf7-4bc9-9a35-fb8ef1149ff7", "product_description": "Placa de Vídeo RTX 3060"}, "customer_info": {"customer_id": "b9457719-1ba2-41c4-bfd7-a0315f6580a8", "customer_name": "Luiza Nascimento", "customer_phone_number": "0500-045-9494"}, "payment_info": {"payment_type": "credit_card", "card_number": "30584626592452", "provider": "JCB 16 digit", "expire": "12/27", "security_code": "250"}, "delivery_address": {"zip_code": "35088113", "country": "Brazil", "state": "Espírito Santo", "city": "Martins", "street": "Chácara Lorenzo Teixeira", "number": "524"}, "order_created_at": "2023-05-28 08:44:47"}