{"order_id": "6468a818-4844-11ee-aa37-00155d2a76eb", "order_total": 149999, "product_info": {"product_id": "e91cb273-e2d0-4f35-958f-8b406a1e53d6", "product_description": "Monitor Gamer Asus"}, "customer_info": {"customer_id": "6e2afe76-63a4-437b-a494-5ceb83f2805a", "customer_name": "Nathan Pereira", "customer_phone_number": "+55 71 6628-0505"}, "payment_info": {"payment_type": "credit_card", "card_number": "2259750401287507", "provider": "JCB 16 digit", "expire": "11/29", "security_code": "831"}, "delivery_address": {"zip_code": "41309202", "country": "Brazil", "state": "Distrito Federal", "city": "Oliveira de Goiás", "street": "Distrito Souza", "number": "50"}, "order_created_at": "2023-05-30 04:27:23"}