{"order_id": "4bacf090-4844-11ee-aa37-00155d2a76eb", "order_total": 13000, "product_info": {"product_id": "405d00c0-6ba4-4b35-affb-46fe368dee5b", "product_description": "Mouse Gamer HyperX"}, "customer_info": {"customer_id": "140a5ac8-7141-4201-9141-670ee575971c", "customer_name": "Ana Clara Viana", "customer_phone_number": "(041) 2076 9587"}, "payment_info": {"payment_type": "credit_card", "card_number": "3567359798094156", "provider": "American Express", "expire": "02/29", "security_code": "445"}, "delivery_address": {"zip_code": "04921158", "country": "Brazil", "state": "Espírito Santo", "city": "da Rosa de Costa", "street": "Pátio da Rosa", "number": "715"}, "order_created_at": "2023-05-08 17:16:33"}